{
  "소나": {
    "ranking": 4,
    "pickRate": "5.10",
    "count": 8347,
    "winRate": "56.97",
    "duoChampionIds": [
      17,
      18,
      19
    ],
    "opTier": 1,
    "isHoney": true,
    "isOp": false
  },
  "피들스틱": {
    "ranking": 8,
    "pickRate": "6.14",
    "count": 10057,
    "winRate": "55.61",
    "duoChampionIds": [
      35,
      36,
      17
    ],
    "opTier": 1,
    "isHoney": true,
    "isOp": false
  },
  "쉔": {
    "ranking": 16,
    "pickRate": "5.10",
    "count": 8350,
    "winRate": "55.34",
    "duoChampionIds": [
      50,
      51,
      52
    ],
    "opTier": 2,
    "isHoney": false,
    "isOp": false
  },
  "마오카이": {
    "ranking": 7,
    "pickRate": "7.25",
    "count": 11870,
    "winRate": "54.96",
    "duoChampionIds": [
      67,
      17,
      68
    ],
    "opTier": 1,
    "isHoney": true,
    "isOp": false
  },
  "세트": {
    "ranking": 6,
    "pickRate": "7.79",
    "count": 12743,
    "winRate": "54.92",
    "duoChampionIds": [
      51,
      82,
      83
    ],
    "opTier": 1,
    "isHoney": true,
    "isOp": false
  },
  "제라스": {
    "ranking": 2,
    "pickRate": "10.08",
    "count": 16505,
    "winRate": "54.91",
    "duoChampionIds": [
      96,
      97,
      98
    ],
    "opTier": 1,
    "isHoney": true,
    "isOp": true
  },
  "징크스": {
    "ranking": 1,
    "pickRate": "12.11",
    "count": 19823,
    "winRate": "54.82",
    "duoChampionIds": [
      110,
      32,
      111
    ],
    "opTier": 1,
    "isHoney": true,
    "isOp": true
  },
  "사이온": {
    "ranking": 31,
    "pickRate": "4.29",
    "count": 7019,
    "winRate": "54.38",
    "duoChampionIds": [
      126,
      127,
      128
    ],
    "opTier": 2,
    "isHoney": false,
    "isOp": false
  },
  "갈리오": {
    "ranking": 19,
    "pickRate": "6.09",
    "count": 9961,
    "winRate": "54.31",
    "duoChampionIds": [
      143,
      17,
      144
    ],
    "opTier": 2,
    "isHoney": false,
    "isOp": false
  },
  "나미": {
    "ranking": 35,
    "pickRate": "4.42",
    "count": 7232,
    "winRate": "53.94",
    "duoChampionIds": [
      158,
      67,
      143
    ],
    "opTier": 2,
    "isHoney": false,
    "isOp": false
  },
  "하이머딩거": {
    "ranking": 37,
    "pickRate": "4.68",
    "count": 7668,
    "winRate": "53.66",
    "duoChampionIds": [
      172,
      173,
      174
    ],
    "opTier": 2,
    "isHoney": false,
    "isOp": false
  },
  "자이라": {
    "ranking": 26,
    "pickRate": "5.84",
    "count": 9561,
    "winRate": "53.57",
    "duoChampionIds": [
      46,
      173,
      188
    ],
    "opTier": 2,
    "isHoney": false,
    "isOp": false
  },
  "모르가나": {
    "ranking": 3,
    "pickRate": "11.02",
    "count": 18038,
    "winRate": "53.50",
    "duoChampionIds": [
      201,
      202,
      203
    ],
    "opTier": 1,
    "isHoney": true,
    "isOp": true
  },
  "브라움": {
    "ranking": 40,
    "pickRate": "4.93",
    "count": 8069,
    "winRate": "53.38",
    "duoChampionIds": [
      51,
      215,
      216
    ],
    "opTier": 2,
    "isHoney": false,
    "isOp": false
  },
  "야스오": {
    "ranking": 20,
    "pickRate": "7.39",
    "count": 12099,
    "winRate": "53.34",
    "duoChampionIds": [
      230,
      11,
      231
    ],
    "opTier": 2,
    "isHoney": false,
    "isOp": false
  },
  "케넨": {
    "ranking": 39,
    "pickRate": "5.06",
    "count": 8288,
    "winRate": "53.31",
    "duoChampionIds": [
      245,
      13,
      215
    ],
    "opTier": 2,
    "isHoney": false,
    "isOp": false
  },
  "직스": {
    "ranking": 11,
    "pickRate": "9.37",
    "count": 15340,
    "winRate": "53.17",
    "duoChampionIds": [
      201,
      64,
      47
    ],
    "opTier": 2,
    "isHoney": false,
    "isOp": false
  },
  "벨코즈": {
    "ranking": 15,
    "pickRate": "8.52",
    "count": 13949,
    "winRate": "53.06",
    "duoChampionIds": [
      271,
      51,
      272
    ],
    "opTier": 2,
    "isHoney": false,
    "isOp": false
  },
  "브랜드": {
    "ranking": 10,
    "pickRate": "9.62",
    "count": 15754,
    "winRate": "53.03",
    "duoChampionIds": [
      285,
      286,
      110
    ],
    "opTier": 2,
    "isHoney": false,
    "isOp": false
  },
  "말자하": {
    "ranking": 23,
    "pickRate": "7.34",
    "count": 12022,
    "winRate": "53.01",
    "duoChampionIds": [
      96,
      79,
      299
    ],
    "opTier": 2,
    "isHoney": false,
    "isOp": false
  },
  "나르": {
    "ranking": 58,
    "pickRate": "3.66",
    "count": 5999,
    "winRate": "52.99",
    "duoChampionIds": [
      313,
      121,
      47
    ],
    "opTier": 3,
    "isHoney": false,
    "isOp": false
  },
  "흐웨이": {
    "ranking": 29,
    "pickRate": "6.38",
    "count": 10440,
    "winRate": "52.97",
    "duoChampionIds": [
      327,
      127,
      328
    ],
    "opTier": 2,
    "isHoney": false,
    "isOp": false
  },
  "렐": {
    "ranking": 74,
    "pickRate": "2.61",
    "count": 4274,
    "winRate": "52.97",
    "duoChampionIds": [
      324,
      340,
      67
    ],
    "opTier": 3,
    "isHoney": false,
    "isOp": false
  },
  "알리스타": {
    "ranking": 36,
    "pickRate": "5.74",
    "count": 9398,
    "winRate": "52.93",
    "duoChampionIds": [
      13,
      216,
      353
    ],
    "opTier": 2,
    "isHoney": false,
    "isOp": false
  },
  "자야": {
    "ranking": 12,
    "pickRate": "9.65",
    "count": 15796,
    "winRate": "52.90",
    "duoChampionIds": [
      230,
      201,
      78
    ],
    "opTier": 2,
    "isHoney": false,
    "isOp": false
  },
  "아이번": {
    "ranking": 62,
    "pickRate": "3.52",
    "count": 5766,
    "winRate": "52.88",
    "duoChampionIds": [
      323,
      227,
      363
    ],
    "opTier": 3,
    "isHoney": false,
    "isOp": false
  },
  "바루스": {
    "ranking": 5,
    "pickRate": "12.15",
    "count": 19887,
    "winRate": "52.55",
    "duoChampionIds": [
      110,
      13,
      64
    ],
    "opTier": 1,
    "isHoney": true,
    "isOp": false
  },
  "카서스": {
    "ranking": 41,
    "pickRate": "5.74",
    "count": 9397,
    "winRate": "52.48",
    "duoChampionIds": [
      401,
      387,
      398
    ],
    "opTier": 2,
    "isHoney": false,
    "isOp": false
  },
  "밀리오": {
    "ranking": 67,
    "pickRate": "3.91",
    "count": 6404,
    "winRate": "52.47",
    "duoChampionIds": [
      216,
      285,
      98
    ],
    "opTier": 3,
    "isHoney": false,
    "isOp": false
  },
  "렉사이": {
    "ranking": 111,
    "pickRate": "1.12",
    "count": 1840,
    "winRate": "52.39",
    "duoChampionIds": [],
    "opTier": 3,
    "isHoney": false,
    "isOp": false
  },
  "소라카": {
    "ranking": 43,
    "pickRate": "5.83",
    "count": 9542,
    "winRate": "52.26",
    "duoChampionIds": [
      11,
      185,
      17
    ],
    "opTier": 2,
    "isHoney": false,
    "isOp": false
  },
  "탈리야": {
    "ranking": 54,
    "pickRate": "4.96",
    "count": 8125,
    "winRate": "52.23",
    "duoChampionIds": [
      453,
      454,
      227
    ],
    "opTier": 2,
    "isHoney": false,
    "isOp": false
  },
  "시비르": {
    "ranking": 24,
    "pickRate": "8.55",
    "count": 13992,
    "winRate": "52.21",
    "duoChampionIds": [
      231,
      412,
      202
    ],
    "opTier": 2,
    "isHoney": false,
    "isOp": false
  },
  "다이애나": {
    "ranking": 59,
    "pickRate": "4.70",
    "count": 7688,
    "winRate": "52.17",
    "duoChampionIds": [
      480,
      481,
      98
    ],
    "opTier": 3,
    "isHoney": false,
    "isOp": false
  },
  "멜": {
    "ranking": 22,
    "pickRate": "8.91",
    "count": 14584,
    "winRate": "52.12",
    "duoChampionIds": [
      13,
      493,
      494
    ],
    "opTier": 2,
    "isHoney": false,
    "isOp": false
  },
  "타릭": {
    "ranking": 110,
    "pickRate": "1.63",
    "count": 2661,
    "winRate": "52.09",
    "duoChampionIds": [
      19,
      506,
      82
    ],
    "opTier": 3,
    "isHoney": false,
    "isOp": false
  },
  "쓰레쉬": {
    "ranking": 17,
    "pickRate": "10.14",
    "count": 16596,
    "winRate": "51.99",
    "duoChampionIds": [
      111,
      450,
      13
    ],
    "opTier": 2,
    "isHoney": false,
    "isOp": false
  },
  "노틸러스": {
    "ranking": 30,
    "pickRate": "7.76",
    "count": 12701,
    "winRate": "51.99",
    "duoChampionIds": [
      282,
      203,
      527
    ],
    "opTier": 2,
    "isHoney": false,
    "isOp": false
  },
  "뽀삐": {
    "ranking": 66,
    "pickRate": "4.69",
    "count": 7675,
    "winRate": "51.90",
    "duoChampionIds": [
      242,
      450,
      539
    ],
    "opTier": 3,
    "isHoney": false,
    "isOp": false
  },
  "트런들": {
    "ranking": 92,
    "pickRate": "2.84",
    "count": 4649,
    "winRate": "51.90",
    "duoChampionIds": [
      363,
      68,
      296
    ],
    "opTier": 3,
    "isHoney": false,
    "isOp": false
  },
  "애쉬": {
    "ranking": 9,
    "pickRate": "12.19",
    "count": 19947,
    "winRate": "51.83",
    "duoChampionIds": [
      310,
      562,
      412
    ],
    "opTier": 1,
    "isHoney": false,
    "isOp": false
  },
  "잔나": {
    "ranking": 51,
    "pickRate": "5.71",
    "count": 9347,
    "winRate": "51.82",
    "duoChampionIds": [
      93,
      202,
      128
    ],
    "opTier": 2,
    "isHoney": false,
    "isOp": false
  },
  "신 짜오": {
    "ranking": 75,
    "pickRate": "3.90",
    "count": 6390,
    "winRate": "51.82",
    "duoChampionIds": [
      63,
      11,
      281
    ],
    "opTier": 3,
    "isHoney": false,
    "isOp": false
  },
  "빅토르": {
    "ranking": 38,
    "pickRate": "7.48",
    "count": 12240,
    "winRate": "51.70",
    "duoChampionIds": [
      363,
      596,
      562
    ],
    "opTier": 2,
    "isHoney": false,
    "isOp": false
  },
  "케일": {
    "ranking": 42,
    "pickRate": "6.79",
    "count": 11110,
    "winRate": "51.70",
    "duoChampionIds": [
      67,
      13,
      32
    ],
    "opTier": 2,
    "isHoney": false,
    "isOp": false
  },
  "초가스": {
    "ranking": 33,
    "pickRate": "8.02",
    "count": 13124,
    "winRate": "51.68",
    "duoChampionIds": [
      310,
      13,
      8
    ],
    "opTier": 2,
    "isHoney": false,
    "isOp": false
  },
  "유미": {
    "ranking": 53,
    "pickRate": "5.77",
    "count": 9437,
    "winRate": "51.65",
    "duoChampionIds": [
      216,
      631,
      144
    ],
    "opTier": 2,
    "isHoney": false,
    "isOp": false
  },
  "레오나": {
    "ranking": 60,
    "pickRate": "5.35",
    "count": 8749,
    "winRate": "51.64",
    "duoChampionIds": [
      51,
      643,
      477
    ],
    "opTier": 3,
    "isHoney": false,
    "isOp": false
  },
  "코그모": {
    "ranking": 44,
    "pickRate": "6.81",
    "count": 11153,
    "winRate": "51.58",
    "duoChampionIds": [
      143,
      313,
      631
    ],
    "opTier": 2,
    "isHoney": false,
    "isOp": false
  },
  "올라프": {
    "ranking": 113,
    "pickRate": "1.60",
    "count": 2613,
    "winRate": "51.51",
    "duoChampionIds": [
      96,
      453,
      282
    ],
    "opTier": 4,
    "isHoney": false,
    "isOp": false
  },
  "스웨인": {
    "ranking": 50,
    "pickRate": "6.26",
    "count": 10246,
    "winRate": "51.50",
    "duoChampionIds": [
      47,
      17,
      13
    ],
    "opTier": 2,
    "isHoney": false,
    "isOp": false
  },
  "그라가스": {
    "ranking": 52,
    "pickRate": "6.09",
    "count": 9963,
    "winRate": "51.50",
    "duoChampionIds": [
      36,
      691,
      155
    ],
    "opTier": 2,
    "isHoney": false,
    "isOp": false
  },
  "오공": {
    "ranking": 64,
    "pickRate": "5.35",
    "count": 8751,
    "winRate": "51.47",
    "duoChampionIds": [
      245,
      702,
      703
    ],
    "opTier": 3,
    "isHoney": false,
    "isOp": false
  },
  "리산드라": {
    "ranking": 47,
    "pickRate": "6.73",
    "count": 11013,
    "winRate": "51.35",
    "duoChampionIds": [
      715,
      230,
      231
    ],
    "opTier": 2,
    "isHoney": false,
    "isOp": false
  },
  "케이틀린": {
    "ranking": 13,
    "pickRate": "12.26",
    "count": 20071,
    "winRate": "51.33",
    "duoChampionIds": [
      64,
      286,
      198
    ],
    "opTier": 2,
    "isHoney": false,
    "isOp": false
  },
  "오른": {
    "ranking": 91,
    "pickRate": "3.67",
    "count": 6011,
    "winRate": "51.29",
    "duoChampionIds": [
      374,
      17,
      741
    ],
    "opTier": 3,
    "isHoney": false,
    "isOp": false
  },
  "럭스": {
    "ranking": 18,
    "pickRate": "11.17",
    "count": 18283,
    "winRate": "51.23",
    "duoChampionIds": [
      98,
      755,
      64
    ],
    "opTier": 2,
    "isHoney": false,
    "isOp": false
  },
  "진": {
    "ranking": 14,
    "pickRate": "12.56",
    "count": 20566,
    "winRate": "51.16",
    "duoChampionIds": [
      562,
      765,
      766
    ],
    "opTier": 2,
    "isHoney": false,
    "isOp": false
  },
  "베인": {
    "ranking": 25,
    "pickRate": "9.60",
    "count": 15711,
    "winRate": "51.16",
    "duoChampionIds": [
      449,
      691,
      46
    ],
    "opTier": 2,
    "isHoney": false,
    "isOp": false
  },
  "문도 박사": {
    "ranking": 76,
    "pickRate": "4.82",
    "count": 7882,
    "winRate": "51.08",
    "duoChampionIds": [
      123,
      299,
      324
    ],
    "opTier": 3,
    "isHoney": false,
    "isOp": false
  },
  "나서스": {
    "ranking": 108,
    "pickRate": "3.06",
    "count": 5004,
    "winRate": "51.08",
    "duoChampionIds": [
      96,
      93,
      313
    ],
    "opTier": 3,
    "isHoney": false,
    "isOp": false
  },
  "트위스티드 페이트": {
    "ranking": 32,
    "pickRate": "9.13",
    "count": 14940,
    "winRate": "51.03",
    "duoChampionIds": [
      46,
      36,
      227
    ],
    "opTier": 2,
    "isHoney": false,
    "isOp": false
  },
  "판테온": {
    "ranking": 45,
    "pickRate": "7.29",
    "count": 11934,
    "winRate": "51.01",
    "duoChampionIds": [
      824,
      172,
      741
    ],
    "opTier": 2,
    "isHoney": false,
    "isOp": false
  },
  "니코": {
    "ranking": 55,
    "pickRate": "6.55",
    "count": 10728,
    "winRate": "51.00",
    "duoChampionIds": [
      52,
      837,
      126
    ],
    "opTier": 3,
    "isHoney": false,
    "isOp": false
  },
  "레나타 글라스크": {
    "ranking": 88,
    "pickRate": "4.15",
    "count": 6785,
    "winRate": "50.98",
    "duoChampionIds": [
      64,
      724,
      313
    ],
    "opTier": 3,
    "isHoney": false,
    "isOp": false
  },
  "사미라": {
    "ranking": 69,
    "pickRate": "6.03",
    "count": 9876,
    "winRate": "50.80",
    "duoChampionIds": [
      51,
      835,
      47
    ],
    "opTier": 3,
    "isHoney": false,
    "isOp": false
  },
  "조이": {
    "ranking": 70,
    "pickRate": "5.91",
    "count": 9668,
    "winRate": "50.74",
    "duoChampionIds": [
      401,
      13,
      36
    ],
    "opTier": 3,
    "isHoney": false,
    "isOp": false
  },
  "리븐": {
    "ranking": 109,
    "pickRate": "3.40",
    "count": 5572,
    "winRate": "50.74",
    "duoChampionIds": [
      241,
      605,
      324
    ],
    "opTier": 3,
    "isHoney": false,
    "isOp": false
  },
  "럼블": {
    "ranking": 71,
    "pickRate": "5.94",
    "count": 9727,
    "winRate": "50.65",
    "duoChampionIds": [
      140,
      79,
      155
    ],
    "opTier": 3,
    "isHoney": false,
    "isOp": false
  },
  "애니": {
    "ranking": 81,
    "pickRate": "5.40",
    "count": 8838,
    "winRate": "50.52",
    "duoChampionIds": [
      227,
      121,
      837
    ],
    "opTier": 3,
    "isHoney": false,
    "isOp": false
  },
  "갱플랭크": {
    "ranking": 83,
    "pickRate": "5.17",
    "count": 8461,
    "winRate": "50.49",
    "duoChampionIds": [
      17,
      916,
      63
    ],
    "opTier": 3,
    "isHoney": false,
    "isOp": false
  },
  "바이": {
    "ranking": 100,
    "pickRate": "4.32",
    "count": 7078,
    "winRate": "50.49",
    "duoChampionIds": [
      927,
      821,
      50
    ],
    "opTier": 3,
    "isHoney": false,
    "isOp": false
  },
  "오리아나": {
    "ranking": 61,
    "pickRate": "7.07",
    "count": 11574,
    "winRate": "50.39",
    "duoChampionIds": [
      169,
      140,
      227
    ],
    "opTier": 3,
    "isHoney": false,
    "isOp": false
  },
  "탐 켄치": {
    "ranking": 101,
    "pickRate": "4.43",
    "count": 7248,
    "winRate": "50.39",
    "duoChampionIds": [
      231,
      282,
      96
    ],
    "opTier": 3,
    "isHoney": false,
    "isOp": false
  },
  "아리": {
    "ranking": 28,
    "pickRate": "10.84",
    "count": 17749,
    "winRate": "50.28",
    "duoChampionIds": [
      110,
      79,
      738
    ],
    "opTier": 2,
    "isHoney": false,
    "isOp": false
  },
  "이렐리아": {
    "ranking": 103,
    "pickRate": "4.54",
    "count": 7425,
    "winRate": "50.21",
    "duoChampionIds": [
      202,
      548,
      17
    ],
    "opTier": 3,
    "isHoney": false,
    "isOp": false
  },
  "칼리스타": {
    "ranking": 107,
    "pickRate": "4.32",
    "count": 7076,
    "winRate": "50.18",
    "duoChampionIds": [
      242,
      140,
      327
    ],
    "opTier": 3,
    "isHoney": false,
    "isOp": false
  },
  "요릭": {
    "ranking": 131,
    "pickRate": "1.42",
    "count": 2326,
    "winRate": "50.17",
    "duoChampionIds": [
      96,
      959,
      68
    ],
    "opTier": 4,
    "isHoney": false,
    "isOp": false
  },
  "이즈리얼": {
    "ranking": 21,
    "pickRate": "12.68",
    "count": 20748,
    "winRate": "50.16",
    "duoChampionIds": [
      201,
      155,
      19
    ],
    "opTier": 2,
    "isHoney": false,
    "isOp": false
  },
  "일라오이": {
    "ranking": 116,
    "pickRate": "3.01",
    "count": 4923,
    "winRate": "50.09",
    "duoChampionIds": [
      154,
      63,
      437
    ],
    "opTier": 4,
    "isHoney": false,
    "isOp": false
  },
  "릴리아": {
    "ranking": 96,
    "pickRate": "5.03",
    "count": 8238,
    "winRate": "50.07",
    "duoChampionIds": [
      123,
      353,
      188
    ],
    "opTier": 3,
    "isHoney": false,
    "isOp": false
  },
  "티모": {
    "ranking": 46,
    "pickRate": "8.78",
    "count": 14378,
    "winRate": "50.05",
    "duoChampionIds": [
      111,
      79,
      140
    ],
    "opTier": 2,
    "isHoney": false,
    "isOp": false
  },
  "벡스": {
    "ranking": 97,
    "pickRate": "5.04",
    "count": 8252,
    "winRate": "50.05",
    "duoChampionIds": [
      374,
      1053,
      64
    ],
    "opTier": 3,
    "isHoney": false,
    "isOp": false
  },
  "아지르": {
    "ranking": 90,
    "pickRate": "5.36",
    "count": 8777,
    "winRate": "50.04",
    "duoChampionIds": [
      281,
      64,
      155
    ],
    "opTier": 3,
    "isHoney": false,
    "isOp": false
  },
  "룰루": {
    "ranking": 57,
    "pickRate": "7.94",
    "count": 12993,
    "winRate": "49.99",
    "duoChampionIds": [
      477,
      123,
      36
    ],
    "opTier": 3,
    "isHoney": false,
    "isOp": false
  },
  "블리츠크랭크": {
    "ranking": 34,
    "pickRate": "10.81",
    "count": 17700,
    "winRate": "49.93",
    "duoChampionIds": [
      340,
      13,
      36
    ],
    "opTier": 2,
    "isHoney": false,
    "isOp": false
  },
  "라이즈": {
    "ranking": 77,
    "pickRate": "6.48",
    "count": 10605,
    "winRate": "49.90",
    "duoChampionIds": [
      79,
      755,
      712
    ],
    "opTier": 3,
    "isHoney": false,
    "isOp": false
  },
  "세라핀": {
    "ranking": 82,
    "pickRate": "6.19",
    "count": 10137,
    "winRate": "49.90",
    "duoChampionIds": [
      245,
      64,
      242
    ],
    "opTier": 3,
    "isHoney": false,
    "isOp": false
  },
  "자르반 4세": {
    "ranking": 89,
    "pickRate": "5.86",
    "count": 9594,
    "winRate": "49.73",
    "duoChampionIds": [
      32,
      19,
      17
    ],
    "opTier": 3,
    "isHoney": false,
    "isOp": false
  },
  "오로라": {
    "ranking": 104,
    "pickRate": "5.22",
    "count": 8546,
    "winRate": "49.65",
    "duoChampionIds": [
      155,
      79,
      398
    ],
    "opTier": 3,
    "isHoney": false,
    "isOp": false
  },
  "아무무": {
    "ranking": 86,
    "pickRate": "6.30",
    "count": 10314,
    "winRate": "49.61",
    "duoChampionIds": [
      916,
      32,
      67
    ],
    "opTier": 3,
    "isHoney": false,
    "isOp": false
  },
  "미스 포츈": {
    "ranking": 27,
    "pickRate": "12.27",
    "count": 20077,
    "winRate": "49.59",
    "duoChampionIds": [
      202,
      144,
      454
    ],
    "opTier": 2,
    "isHoney": false,
    "isOp": false
  },
  "모데카이저": {
    "ranking": 94,
    "pickRate": "5.94",
    "count": 9726,
    "winRate": "49.50",
    "duoChampionIds": [
      51,
      123,
      198
    ],
    "opTier": 3,
    "isHoney": false,
    "isOp": false
  },
  "아트록스": {
    "ranking": 78,
    "pickRate": "7.11",
    "count": 11636,
    "winRate": "49.45",
    "duoChampionIds": [
      155,
      809,
      398
    ],
    "opTier": 3,
    "isHoney": false,
    "isOp": false
  },
  "애니비아": {
    "ranking": 80,
    "pickRate": "6.96",
    "count": 11393,
    "winRate": "49.45",
    "duoChampionIds": [
      231,
      481,
      64
    ],
    "opTier": 3,
    "isHoney": false,
    "isOp": false
  },
  "다리우스": {
    "ranking": 99,
    "pickRate": "5.79",
    "count": 9470,
    "winRate": "49.44",
    "duoChampionIds": [
      13,
      17,
      340
    ],
    "opTier": 3,
    "isHoney": false,
    "isOp": false
  },
  "아우렐리온 솔": {
    "ranking": 106,
    "pickRate": "5.39",
    "count": 8827,
    "winRate": "49.43",
    "duoChampionIds": [
      328,
      327,
      506
    ],
    "opTier": 3,
    "isHoney": false,
    "isOp": false
  },
  "킨드레드": {
    "ranking": 114,
    "pickRate": "4.07",
    "count": 6668,
    "winRate": "49.40",
    "duoChampionIds": [
      32,
      93,
      350
    ],
    "opTier": 4,
    "isHoney": false,
    "isOp": false
  },
  "아펠리오스": {
    "ranking": 85,
    "pickRate": "6.74",
    "count": 11038,
    "winRate": "49.33",
    "duoChampionIds": [
      13,
      1135,
      123
    ],
    "opTier": 3,
    "isHoney": false,
    "isOp": false
  },
  "잭스": {
    "ranking": 98,
    "pickRate": "5.98",
    "count": 9795,
    "winRate": "49.33",
    "duoChampionIds": [
      231,
      715,
      480
    ],
    "opTier": 3,
    "isHoney": false,
    "isOp": false
  },
  "세주아니": {
    "ranking": 127,
    "pickRate": "3.03",
    "count": 4959,
    "winRate": "49.32",
    "duoChampionIds": [
      64,
      1123,
      93
    ],
    "opTier": 4,
    "isHoney": false,
    "isOp": false
  },
  "엘리스": {
    "ranking": 132,
    "pickRate": "2.37",
    "count": 3884,
    "winRate": "49.30",
    "duoChampionIds": [
      82,
      286,
      36
    ],
    "opTier": 4,
    "isHoney": false,
    "isOp": false
  },
  "카르마": {
    "ranking": 56,
    "pickRate": "9.23",
    "count": 15103,
    "winRate": "49.26",
    "duoChampionIds": [
      401,
      64,
      231
    ],
    "opTier": 3,
    "isHoney": false,
    "isOp": false
  },
  "카시오페아": {
    "ranking": 123,
    "pickRate": "3.39",
    "count": 5553,
    "winRate": "49.23",
    "duoChampionIds": [
      127,
      296,
      17
    ],
    "opTier": 4,
    "isHoney": false,
    "isOp": false
  },
  "라칸": {
    "ranking": 126,
    "pickRate": "3.22",
    "count": 5265,
    "winRate": "49.19",
    "duoChampionIds": [
      52,
      340,
      363
    ],
    "opTier": 4,
    "isHoney": false,
    "isOp": false
  },
  "세나": {
    "ranking": 63,
    "pickRate": "8.93",
    "count": 14609,
    "winRate": "49.12",
    "duoChampionIds": [
      617,
      327,
      19
    ],
    "opTier": 3,
    "isHoney": false,
    "isOp": false
  },
  "닐라": {
    "ranking": 129,
    "pickRate": "3.20",
    "count": 5230,
    "winRate": "49.12",
    "duoChampionIds": [
      691,
      11,
      350
    ],
    "opTier": 4,
    "isHoney": false,
    "isOp": false
  },
  "레넥톤": {
    "ranking": 118,
    "pickRate": "3.98",
    "count": 6511,
    "winRate": "49.09",
    "duoChampionIds": [
      202,
      242,
      605
    ],
    "opTier": 4,
    "isHoney": false,
    "isOp": false
  },
  "제이스": {
    "ranking": 48,
    "pickRate": "10.48",
    "count": 17160,
    "winRate": "49.00",
    "duoChampionIds": [
      527,
      79,
      493
    ],
    "opTier": 2,
    "isHoney": false,
    "isOp": false
  },
  "니달리": {
    "ranking": 49,
    "pickRate": "10.69",
    "count": 17499,
    "winRate": "48.75",
    "duoChampionIds": [
      36,
      46,
      203
    ],
    "opTier": 2,
    "isHoney": false,
    "isOp": false
  },
  "사일러스": {
    "ranking": 72,
    "pickRate": "8.98",
    "count": 14693,
    "winRate": "48.66",
    "duoChampionIds": [
      340,
      493,
      755
    ],
    "opTier": 3,
    "isHoney": false,
    "isOp": false
  },
  "트리스타나": {
    "ranking": 73,
    "pickRate": "9.02",
    "count": 14758,
    "winRate": "48.62",
    "duoChampionIds": [
      231,
      268,
      68
    ],
    "opTier": 3,
    "isHoney": false,
    "isOp": false
  },
  "자크": {
    "ranking": 125,
    "pickRate": "4.06",
    "count": 6651,
    "winRate": "48.61",
    "duoChampionIds": [
      47,
      98,
      110
    ],
    "opTier": 4,
    "isHoney": false,
    "isOp": false
  },
  "샤코": {
    "ranking": 102,
    "pickRate": "6.93",
    "count": 11345,
    "winRate": "48.54",
    "duoChampionIds": [
      401,
      363,
      51
    ],
    "opTier": 3,
    "isHoney": false,
    "isOp": false
  },
  "카밀": {
    "ranking": 136,
    "pickRate": "2.07",
    "count": 3387,
    "winRate": "48.51",
    "duoChampionIds": [
      98,
      712,
      96
    ],
    "opTier": 4,
    "isHoney": false,
    "isOp": false
  },
  "트위치": {
    "ranking": 87,
    "pickRate": "7.93",
    "count": 12982,
    "winRate": "48.45",
    "duoChampionIds": [
      230,
      617,
      32
    ],
    "opTier": 3,
    "isHoney": false,
    "isOp": false
  },
  "우르곳": {
    "ranking": 133,
    "pickRate": "2.67",
    "count": 4363,
    "winRate": "48.41",
    "duoChampionIds": [
      363,
      506,
      203
    ],
    "opTier": 4,
    "isHoney": false,
    "isOp": false
  },
  "말파이트": {
    "ranking": 68,
    "pickRate": "9.96",
    "count": 16295,
    "winRate": "48.32",
    "duoChampionIds": [
      724,
      98,
      216
    ],
    "opTier": 3,
    "isHoney": false,
    "isOp": false
  },
  "블라디미르": {
    "ranking": 122,
    "pickRate": "4.91",
    "count": 8039,
    "winRate": "48.24",
    "duoChampionIds": [
      281,
      68,
      450
    ],
    "opTier": 4,
    "isHoney": false,
    "isOp": false
  },
  "코르키": {
    "ranking": 112,
    "pickRate": "6.27",
    "count": 10261,
    "winRate": "48.15",
    "duoChampionIds": [
      215,
      548,
      453
    ],
    "opTier": 3,
    "isHoney": false,
    "isOp": false
  },
  "베이가": {
    "ranking": 79,
    "pickRate": "9.16",
    "count": 15000,
    "winRate": "48.11",
    "duoChampionIds": [
      201,
      79,
      562
    ],
    "opTier": 3,
    "isHoney": false,
    "isOp": false
  },
  "스몰더": {
    "ranking": 95,
    "pickRate": "7.95",
    "count": 13006,
    "winRate": "48.10",
    "duoChampionIds": [
      47,
      64,
      155
    ],
    "opTier": 3,
    "isHoney": false,
    "isOp": false
  },
  "제리": {
    "ranking": 117,
    "pickRate": "5.54",
    "count": 9060,
    "winRate": "48.00",
    "duoChampionIds": [
      47,
      231,
      13
    ],
    "opTier": 4,
    "isHoney": false,
    "isOp": false
  },
  "트린다미어": {
    "ranking": 135,
    "pickRate": "3.04",
    "count": 4974,
    "winRate": "47.99",
    "duoChampionIds": [
      50,
      96,
      174
    ],
    "opTier": 4,
    "isHoney": false,
    "isOp": false
  },
  "루시안": {
    "ranking": 65,
    "pickRate": "11.03",
    "count": 18051,
    "winRate": "47.85",
    "duoChampionIds": [
      13,
      202,
      154
    ],
    "opTier": 3,
    "isHoney": false,
    "isOp": false
  },
  "비에고": {
    "ranking": 120,
    "pickRate": "5.74",
    "count": 9402,
    "winRate": "47.76",
    "duoChampionIds": [
      79,
      835,
      282
    ],
    "opTier": 4,
    "isHoney": false,
    "isOp": false
  },
  "워윅": {
    "ranking": 144,
    "pickRate": "2.25",
    "count": 3675,
    "winRate": "47.65",
    "duoChampionIds": [
      36,
      216,
      282
    ],
    "opTier": 4,
    "isHoney": false,
    "isOp": false
  },
  "람머스": {
    "ranking": 146,
    "pickRate": "2.15",
    "count": 3515,
    "winRate": "47.65",
    "duoChampionIds": [
      1297,
      323,
      281
    ],
    "opTier": 4,
    "isHoney": false,
    "isOp": false
  },
  "리 신": {
    "ranking": 84,
    "pickRate": "9.52",
    "count": 15577,
    "winRate": "47.59",
    "duoChampionIds": [
      412,
      282,
      13
    ],
    "opTier": 3,
    "isHoney": false,
    "isOp": false
  },
  "요네": {
    "ranking": 105,
    "pickRate": "8.24",
    "count": 13483,
    "winRate": "47.58",
    "duoChampionIds": [
      755,
      13,
      449
    ],
    "opTier": 3,
    "isHoney": false,
    "isOp": false
  },
  "신드라": {
    "ranking": 128,
    "pickRate": "5.29",
    "count": 8651,
    "winRate": "47.57",
    "duoChampionIds": [
      79,
      741,
      127
    ],
    "opTier": 4,
    "isHoney": false,
    "isOp": false
  },
  "볼리베어": {
    "ranking": 143,
    "pickRate": "2.61",
    "count": 4272,
    "winRate": "47.35",
    "duoChampionIds": [
      268,
      50,
      296
    ],
    "opTier": 4,
    "isHoney": false,
    "isOp": false
  },
  "피즈": {
    "ranking": 130,
    "pickRate": "5.37",
    "count": 8788,
    "winRate": "47.29",
    "duoChampionIds": [
      169,
      184,
      323
    ],
    "opTier": 4,
    "isHoney": false,
    "isOp": false
  },
  "크산테": {
    "ranking": 138,
    "pickRate": "3.24",
    "count": 5296,
    "winRate": "47.17",
    "duoChampionIds": [
      296,
      653,
      17
    ],
    "opTier": 4,
    "isHoney": false,
    "isOp": false
  },
  "아크샨": {
    "ranking": 137,
    "pickRate": "3.51",
    "count": 5744,
    "winRate": "47.09",
    "duoChampionIds": [
      712,
      463,
      268
    ],
    "opTier": 4,
    "isHoney": false,
    "isOp": false
  },
  "질리언": {
    "ranking": 121,
    "pickRate": "6.87",
    "count": 11246,
    "winRate": "46.95",
    "duoChampionIds": [
      449,
      52,
      169
    ],
    "opTier": 4,
    "isHoney": false,
    "isOp": false
  },
  "스카너": {
    "ranking": 141,
    "pickRate": "3.51",
    "count": 5743,
    "winRate": "46.82",
    "duoChampionIds": [
      32,
      593,
      17
    ],
    "opTier": 4,
    "isHoney": false,
    "isOp": false
  },
  "그레이브즈": {
    "ranking": 115,
    "pickRate": "7.62",
    "count": 12478,
    "winRate": "46.81",
    "duoChampionIds": [
      665,
      328,
      63
    ],
    "opTier": 4,
    "isHoney": false,
    "isOp": false
  },
  "클레드": {
    "ranking": 156,
    "pickRate": "0.68",
    "count": 1114,
    "winRate": "46.77",
    "duoChampionIds": [],
    "opTier": 5,
    "isHoney": false,
    "isOp": false
  },
  "신지드": {
    "ranking": 139,
    "pickRate": "3.80",
    "count": 6215,
    "winRate": "46.71",
    "duoChampionIds": [
      677,
      480,
      286
    ],
    "opTier": 4,
    "isHoney": false,
    "isOp": false
  },
  "케인": {
    "ranking": 148,
    "pickRate": "2.60",
    "count": 4255,
    "winRate": "46.58",
    "duoChampionIds": [
      268,
      539,
      67
    ],
    "opTier": 4,
    "isHoney": false,
    "isOp": false
  },
  "퀸": {
    "ranking": 134,
    "pickRate": "4.91",
    "count": 8041,
    "winRate": "46.55",
    "duoChampionIds": [
      242,
      374,
      1103
    ],
    "opTier": 4,
    "isHoney": false,
    "isOp": false
  },
  "피오라": {
    "ranking": 149,
    "pickRate": "2.44",
    "count": 3999,
    "winRate": "46.44",
    "duoChampionIds": [
      128,
      350,
      93
    ],
    "opTier": 5,
    "isHoney": false,
    "isOp": false
  },
  "카이사": {
    "ranking": 93,
    "pickRate": "11.43",
    "count": 18717,
    "winRate": "46.12",
    "duoChampionIds": [
      653,
      110,
      64
    ],
    "opTier": 3,
    "isHoney": false,
    "isOp": false
  },
  "제드": {
    "ranking": 119,
    "pickRate": "8.32",
    "count": 13626,
    "winRate": "46.05",
    "duoChampionIds": [
      47,
      449,
      296
    ],
    "opTier": 4,
    "isHoney": false,
    "isOp": false
  },
  "마스터 이": {
    "ranking": 140,
    "pickRate": "4.69",
    "count": 7675,
    "winRate": "45.95",
    "duoChampionIds": [
      68,
      123,
      64
    ],
    "opTier": 4,
    "isHoney": false,
    "isOp": false
  },
  "그웬": {
    "ranking": 151,
    "pickRate": "3.08",
    "count": 5044,
    "winRate": "45.62",
    "duoChampionIds": [
      93,
      68,
      154
    ],
    "opTier": 5,
    "isHoney": false,
    "isOp": false
  },
  "브라이어": {
    "ranking": 158,
    "pickRate": "1.51",
    "count": 2477,
    "winRate": "45.58",
    "duoChampionIds": [
      68,
      539,
      203
    ],
    "opTier": 5,
    "isHoney": false,
    "isOp": false
  },
  "파이크": {
    "ranking": 124,
    "pickRate": "8.60",
    "count": 14073,
    "winRate": "45.53",
    "duoChampionIds": [
      281,
      412,
      11
    ],
    "opTier": 4,
    "isHoney": false,
    "isOp": false
  },
  "가렌": {
    "ranking": 145,
    "pickRate": "5.15",
    "count": 8431,
    "winRate": "45.38",
    "duoChampionIds": [
      174,
      79,
      123
    ],
    "opTier": 4,
    "isHoney": false,
    "isOp": false
  },
  "암베사": {
    "ranking": 152,
    "pickRate": "3.07",
    "count": 5026,
    "winRate": "45.28",
    "duoChampionIds": [
      821,
      47,
      68
    ],
    "opTier": 5,
    "isHoney": false,
    "isOp": false
  },
  "카직스": {
    "ranking": 147,
    "pickRate": "5.34",
    "count": 8744,
    "winRate": "45.01",
    "duoChampionIds": [
      32,
      453,
      677
    ],
    "opTier": 4,
    "isHoney": false,
    "isOp": false
  },
  "우디르": {
    "ranking": 159,
    "pickRate": "2.22",
    "count": 3627,
    "winRate": "44.94",
    "duoChampionIds": [
      96,
      203,
      36
    ],
    "opTier": 5,
    "isHoney": false,
    "isOp": false
  },
  "녹턴": {
    "ranking": 163,
    "pickRate": "2.25",
    "count": 3688,
    "winRate": "44.55",
    "duoChampionIds": [
      62,
      506,
      93
    ],
    "opTier": 5,
    "isHoney": false,
    "isOp": false
  },
  "에코": {
    "ranking": 150,
    "pickRate": "4.68",
    "count": 7660,
    "winRate": "44.41",
    "duoChampionIds": [
      13,
      79,
      328
    ],
    "opTier": 5,
    "isHoney": false,
    "isOp": false
  },
  "탈론": {
    "ranking": 160,
    "pickRate": "2.75",
    "count": 4509,
    "winRate": "44.22",
    "duoChampionIds": [
      93,
      17,
      174
    ],
    "opTier": 5,
    "isHoney": false,
    "isOp": false
  },
  "헤카림": {
    "ranking": 165,
    "pickRate": "1.59",
    "count": 2602,
    "winRate": "44.20",
    "duoChampionIds": [
      453,
      168,
      36
    ],
    "opTier": 5,
    "isHoney": false,
    "isOp": false
  },
  "쉬바나": {
    "ranking": 164,
    "pickRate": "1.89",
    "count": 3089,
    "winRate": "44.03",
    "duoChampionIds": [
      36,
      959,
      539
    ],
    "opTier": 5,
    "isHoney": false,
    "isOp": false
  },
  "이블린": {
    "ranking": 168,
    "pickRate": "1.15",
    "count": 1879,
    "winRate": "43.69",
    "duoChampionIds": [
      173,
      93,
      36
    ],
    "opTier": 5,
    "isHoney": false,
    "isOp": false
  },
  "키아나": {
    "ranking": 166,
    "pickRate": "2.08",
    "count": 3410,
    "winRate": "43.61",
    "duoChampionIds": [
      453,
      50,
      268
    ],
    "opTier": 5,
    "isHoney": false,
    "isOp": false
  },
  "바드": {
    "ranking": 154,
    "pickRate": "5.05",
    "count": 8263,
    "winRate": "43.53",
    "duoChampionIds": [
      185,
      79,
      712
    ],
    "opTier": 5,
    "isHoney": false,
    "isOp": false
  },
  "드레이븐": {
    "ranking": 155,
    "pickRate": "4.94",
    "count": 8094,
    "winRate": "43.43",
    "duoChampionIds": [
      449,
      13,
      64
    ],
    "opTier": 5,
    "isHoney": false,
    "isOp": false
  },
  "나피리": {
    "ranking": 157,
    "pickRate": "4.64",
    "count": 7603,
    "winRate": "43.38",
    "duoChampionIds": [
      702,
      64,
      93
    ],
    "opTier": 5,
    "isHoney": false,
    "isOp": false
  },
  "르블랑": {
    "ranking": 142,
    "pickRate": "8.46",
    "count": 13855,
    "winRate": "43.30",
    "duoChampionIds": [
      374,
      51,
      185
    ],
    "opTier": 4,
    "isHoney": false,
    "isOp": false
  },
  "누누와 윌럼프": {
    "ranking": 161,
    "pickRate": "4.19",
    "count": 6863,
    "winRate": "43.06",
    "duoChampionIds": [
      398,
      215,
      821
    ],
    "opTier": 5,
    "isHoney": false,
    "isOp": false
  },
  "카사딘": {
    "ranking": 167,
    "pickRate": "2.41",
    "count": 3947,
    "winRate": "42.84",
    "duoChampionIds": [
      285,
      821,
      1187
    ],
    "opTier": 5,
    "isHoney": false,
    "isOp": false
  },
  "아칼리": {
    "ranking": 153,
    "pickRate": "6.43",
    "count": 10530,
    "winRate": "42.60",
    "duoChampionIds": [
      255,
      463,
      241
    ],
    "opTier": 5,
    "isHoney": false,
    "isOp": false
  },
  "카타리나": {
    "ranking": 162,
    "pickRate": "5.30",
    "count": 8673,
    "winRate": "42.18",
    "duoChampionIds": [
      398,
      476,
      374
    ],
    "opTier": 5,
    "isHoney": false,
    "isOp": false
  },
  "벨베스": {
    "ranking": 170,
    "pickRate": "1.68",
    "count": 2753,
    "winRate": "41.59",
    "duoChampionIds": [
      216,
      751,
      313
    ],
    "opTier": 5,
    "isHoney": false,
    "isOp": false
  },
  "렝가": {
    "ranking": 169,
    "pickRate": "2.02",
    "count": 3300,
    "winRate": "41.36",
    "duoChampionIds": [],
    "opTier": 5,
    "isHoney": false,
    "isOp": false
  }
}